smace/__init__.py
smace/decisions.py
smace/explainer.py
smace/models.py
smace/rules.py
smace/smace_explanation.py
smace/utils.py
smace-0.0.dist-info/LICENCE.md
smace-0.0.dist-info/METADATA
smace-0.0.dist-info/WHEEL
smace-0.0.dist-info/top_level.txt
smace-0.0.dist-info/RECORD
