Metadata-Version: 2.1
Name: smace
Version: 0.0
Summary: Semi-Model-Agnostic Contextual Explainer library
Home-page: https://github.com/gianluigilopardo/smace
Author: Gianluigi Lopardo
Author-email: Gianluigi.Lopardo@inria.fr
License: UNKNOWN
Project-URL: Homepage, http://github.com/gianluigilopardo/smace
Platform: UNKNOWN
Classifier: License :: OSI Approved :: MIT License
Classifier: Intended Audience :: Science/Research
Classifier: Topic :: Scientific/Engineering
Classifier: Topic :: Scientific/Engineering :: Artificial Intelligence
Classifier: License :: OSI Approved :: MIT License
Classifier: Programming Language :: Python :: 3
Requires-Python: >=3.7
Requires-Dist: numpy (==1.20.3)
Requires-Dist: pandas (==1.2.5)
Requires-Dist: cvxpy (==1.1.15)
Requires-Dist: shap (==0.39.0)
Requires-Dist: lime (==0.2.0.1)
Requires-Dist: matplotlib (==3.4.3)
Requires-Dist: xgboost (==1.4.2)
Requires-Dist: scikit-learn (==0.24.2)
Requires-Dist: scipy (==1.7.1)
